control_unit.v
module control_unit(Opcode, Mem_Write, ACC_Write);
    input [3:0] Opcode;
    output reg Mem_Write;
    output reg ACC_Write;
    
    always @(*) begin
        case(Opcode)
            4'b0000: begin Mem_Write = 1'b0; ACC_Write = 1'b1; end
            4'b0001: begin Mem_Write = 1'b1; ACC_Write = 1'b0; end
            4'b0010: begin Mem_Write = 1'b0; ACC_Write = 1'b1; end
            4'b0011: begin Mem_Write = 1'b0; ACC_Write = 1'b1; end
            4'b0100: begin Mem_Write = 1'b0; ACC_Write = 1'b1; end
            4'b0101: begin Mem_Write = 1'b0; ACC_Write = 1'b1; end
            default: begin Mem_Write = 1'b0; ACC_Write = 1'b0; end
        endcase
    end
endmodule

alu.v
module alu(ACC, RAM_Data, Opcode, ALU_Result);
    input [3:0] ACC;
    input [3:0] RAM_Data;
    input [3:0] Opcode;
    output reg [3:0] ALU_Result;
    
    always @(*) begin
        case(Opcode)
            4'b0000: ALU_Result = RAM_Data;
            4'b0010: ALU_Result = ACC + RAM_Data;
            4'b0011: ALU_Result = ACC - RAM_Data;
            4'b0100: ALU_Result = ACC & RAM_Data;
            4'b0101: ALU_Result = ACC ^ RAM_Data;
            default: ALU_Result = ACC;
        endcase
    end
endmodule

ram.v
module ram(clk, addr, data_in, Mem_Write, data_out);
    input clk;
    input [3:0] addr;
    input [3:0] data_in;
    input Mem_Write;
    output [3:0] data_out;
    
    reg [3:0] ram [0:15];
    integer i;
    
    initial begin
        ram[0] = 4'd2;
        ram[1] = 4'd3;
        ram[2] = 4'd4;
        for(i=3; i<16; i=i+1) ram[i] = 4'd0;
    end
    
    always @(posedge clk) begin
        if(Mem_Write) ram[addr] <= data_in;
    end
    
    assign data_out = ram[addr];
endmodule

rom.v
module rom(addr, instruction);
    input [3:0] addr;
    output [7:0] instruction;
    
    reg [7:0] rom [0:15];
    integer i;
    
    initial begin
        rom[0] = 8'h00;
        rom[1] = 8'h21;
        rom[2] = 8'h32;
        rom[3] = 8'h40;
        rom[4] = 8'h51;
        rom[5] = 8'h13;
        for(i=6; i<16; i=i+1) rom[i] = 8'h00;
    end
    
    assign instruction = rom[addr];
endmodule

pc.v
module pc(clk, rst, pc_out);
    input clk, rst;
    output reg [3:0] pc_out;

    always @(posedge clk or posedge rst) begin
        if(rst) pc_out <= 4'b0000;
        else pc_out <= pc_out + 1'b1;
    end
endmodule

cpu_top.v
module cpu_top(clk, rst, PC_Out, Opcode_Out, RAM_Addr_Out, RAM_Data_Out, ACC_Out, Mem_Write_Out);
    input clk, rst;
    output [3:0] PC_Out;
    output [3:0] Opcode_Out;
    output [3:0] RAM_Addr_Out;
    output [3:0] RAM_Data_Out;
    output [3:0] ACC_Out;
    output Mem_Write_Out;

    wire [3:0] pc_val; // Renamed to avoid conflicting with the module named 'pc'
    wire [7:0] instruction;
    wire [3:0] opcode;
    wire [3:0] ram_addr;
    wire [3:0] ram_data_out;
    wire [3:0] alu_result;
    wire mem_write;
    wire acc_write;
    reg [3:0] ACC;

    assign opcode = instruction[7:4];
    assign ram_addr = instruction[3:0];

    // UPDATED INSTANTIATION NAMES HERE:
    pc PC_inst(.clk(clk), .rst(rst), .pc_out(pc_val));
    rom ROM_inst(.addr(pc_val), .instruction(instruction));
    ram RAM_inst(.clk(clk), .addr(ram_addr), .data_in(ACC), .Mem_Write(mem_write), .data_out(ram_data_out));
    alu ALU_inst(.ACC(ACC), .RAM_Data(ram_data_out), .Opcode(opcode), .ALU_Result(alu_result));
    control_unit CU_inst(.Opcode(opcode), .Mem_Write(mem_write), .ACC_Write(acc_write));

    always @(posedge clk or posedge rst) begin
        if(rst) ACC <= 4'b0000;
        else if(acc_write) ACC <= alu_result;
    end

    assign PC_Out = pc_val;
    assign Opcode_Out = opcode;
    assign RAM_Addr_Out = ram_addr;
    assign RAM_Data_Out = ram_data_out;
    assign ACC_Out = ACC;
    assign Mem_Write_Out = mem_write;

endmodule

tb_cpu.v
`timescale 1ns / 1ps
module tb_cpu;
    reg clk;
    reg rst;
    wire [3:0] PC_Out;
    wire [3:0] Opcode_Out;
    wire [3:0] RAM_Addr_Out;
    wire [3:0] RAM_Data_Out;
    wire [3:0] ACC_Out;
    wire Mem_Write_Out;

    // UPDATED INSTANTIATION HERE:
    cpu_top DUT(
        .clk(clk), 
        .rst(rst), 
        .PC_Out(PC_Out), 
        .Opcode_Out(Opcode_Out), 
        .RAM_Addr_Out(RAM_Addr_Out), 
        .RAM_Data_Out(RAM_Data_Out), 
        .ACC_Out(ACC_Out), 
        .Mem_Write_Out(Mem_Write_Out)
    );

    initial clk = 0;
    always #5 clk = ~clk;

    initial begin
        rst = 1;
        #12;
        rst = 0;
    end

    initial begin
        $dumpfile("waveform.vcd");
        $dumpvars(0, tb_cpu);
    end

    initial begin
        $monitor("Time %0d PC %0d Opcode %0d RAM_Address %0d RAM_Data_Out %0d ACC %0d Mem_Write %0d", 
                 $time, PC_Out, Opcode_Out, RAM_Addr_Out, RAM_Data_Out, ACC_Out, Mem_Write_Out);
    end

    initial begin
        #150;
        $finish;
    end
endmodule

waveform.vcd
$date
	Sat Aug 15 14:04:37 2026
$end
$version
	Icarus Verilog
$end
$timescale
	1ps
$end
$scope module tb_cpu $end
$var wire 4 ! RAM_Data_Out [3:0] $end
$var wire 4 " RAM_Addr_Out [3:0] $end
$var wire 4 # PC_Out [3:0] $end
$var wire 4 $ Opcode_Out [3:0] $end
$var wire 1 % Mem_Write_Out $end
$var wire 4 & ACC_Out [3:0] $end
$var reg 1 ' clk $end
$var reg 1 ( rst $end
$scope module DUT $end
$var wire 4 ) ACC_Out [3:0] $end
$var wire 1 % Mem_Write_Out $end
$var wire 4 * Opcode_Out [3:0] $end
$var wire 4 + PC_Out [3:0] $end
$var wire 4 , RAM_Addr_Out [3:0] $end
$var wire 4 - RAM_Data_Out [3:0] $end
$var wire 1 ' clk $end
$var wire 1 ( rst $end
$var wire 4 . ram_data_out [3:0] $end
$var wire 4 / ram_addr [3:0] $end
$var wire 4 0 pc_val [3:0] $end
$var wire 4 1 opcode [3:0] $end
$var wire 1 2 mem_write $end
$var wire 8 3 instruction [7:0] $end
$var wire 4 4 alu_result [3:0] $end
$var wire 1 5 acc_write $end
$var reg 4 6 ACC [3:0] $end
$scope module ALU_inst $end
$var wire 4 7 ACC [3:0] $end
$var wire 4 8 Opcode [3:0] $end
$var wire 4 9 RAM_Data [3:0] $end
$var reg 4 : ALU_Result [3:0] $end
$upscope $end
$scope module CU_inst $end
$var wire 4 ; Opcode [3:0] $end
$var reg 1 5 ACC_Write $end
$var reg 1 2 Mem_Write $end
$upscope $end
$scope module PC_inst $end
$var wire 1 ' clk $end
$var wire 1 ( rst $end
$var reg 4 < pc_out [3:0] $end
$upscope $end
$scope module RAM_inst $end
$var wire 1 2 Mem_Write $end
$var wire 4 = addr [3:0] $end
$var wire 1 ' clk $end
$var wire 4 > data_in [3:0] $end
$var wire 4 ? data_out [3:0] $end
$var integer 32 @ i [31:0] $end
$upscope $end
$scope module ROM_inst $end
$var wire 4 A addr [3:0] $end
$var wire 8 B instruction [7:0] $end
$var integer 32 C i [31:0] $end
$upscope $end
$upscope $end
$upscope $end
$enddefinitions $end
$comment Show the parameter values. $end
$dumpall
$end
#0
$dumpvars
b10000 C
b0 B
b0 A
b10000 @
b10 ?
b0 >
b0 =
b0 <
b0 ;
b10 :
b10 9
b0 8
b0 7
b0 6
15
b10 4
b0 3
02
b0 1
b0 0
b0 /
b10 .
b10 -
b0 ,
b0 +
b0 *
b0 )
1(
0'
b0 &
0%
b0 $
b0 #
b0 "
b10 !
$end
#5000
1'
#10000
0'
#12000
0(
#15000
b101 4
b101 :
b11 !
b11 -
b11 .
b11 9
b11 ?
b1 "
b1 ,
b1 /
b1 =
b10 $
b10 *
b10 1
b10 8
b10 ;
b100001 3
b100001 B
b1 #
b1 +
b1 0
b1 <
b1 A
b10 &
b10 )
b10 6
b10 7
b10 >
1'
#20000
0'
#25000
b1 4
b1 :
b100 !
b100 -
b100 .
b100 9
b100 ?
b10 "
b10 ,
b10 /
b10 =
b11 $
b11 *
b11 1
b11 8
b11 ;
b101 &
b101 )
b101 6
b101 7
b101 >
b110010 3
b110010 B
b10 #
b10 +
b10 0
b10 <
b10 A
1'
#30000
0'
#35000
b10 !
b10 -
b10 .
b10 9
b10 ?
b0 "
b0 ,
b0 /
b0 =
b100 $
b100 *
b100 1
b100 8
b100 ;
b0 4
b0 :
b1000000 3
b1000000 B
b11 #
b11 +
b11 0
b11 <
b11 A
b1 &
b1 )
b1 6
b1 7
b1 >
1'
#40000
0'
#45000
b11 4
b11 :
b11 !
b11 -
b11 .
b11 9
b11 ?
b1 "
b1 ,
b1 /
b1 =
b101 $
b101 *
b101 1
b101 8
b101 ;
b0 &
b0 )
b0 6
b0 7
b0 >
b1010001 3
b1010001 B
b100 #
b100 +
b100 0
b100 <
b100 A
1'
#50000
0'
#55000
05
1%
12
b0 !
b0 -
b0 .
b0 9
b0 ?
b11 "
b11 ,
b11 /
b11 =
b1 $
b1 *
b1 1
b1 8
b1 ;
b11 4
b11 :
b10011 3
b10011 B
b101 #
b101 +
b101 0
b101 <
b101 A
b11 &
b11 )
b11 6
b11 7
b11 >
1'
#60000
0'
#65000
b10 4
b10 :
15
0%
02
b0 "
b0 ,
b0 /
b0 =
b0 $
b0 *
b0 1
b0 8
b0 ;
b0 3
b0 B
b110 #
b110 +
b110 0
b110 <
b110 A
b10 !
b10 -
b10 .
b10 9
b10 ?
1'
#70000
0'
#75000
b111 #
b111 +
b111 0
b111 <
b111 A
b10 &
b10 )
b10 6
b10 7
b10 >
1'
#80000
0'
#85000
b1000 #
b1000 +
b1000 0
b1000 <
b1000 A
1'
#90000
0'
#95000
b1001 #
b1001 +
b1001 0
b1001 <
b1001 A
1'
#100000
0'
#105000
b1010 #
b1010 +
b1010 0
b1010 <
b1010 A
1'
#110000
0'
#115000
b1011 #
b1011 +
b1011 0
b1011 <
b1011 A
1'
#120000
0'
#125000
b1100 #
b1100 +
b1100 0
b1100 <
b1100 A
1'
#130000
0'
#135000
b1101 #
b1101 +
b1101 0
b1101 <
b1101 A
1'
#140000
0'
#145000
b1110 #
b1110 +
b1110 0
b1110 <
b1110 A
1'
